odoo/addons/l10n_th_withholding_tax_cert_form/README.rst
odoo/addons/l10n_th_withholding_tax_cert_form/__init__.py
odoo/addons/l10n_th_withholding_tax_cert_form/__manifest__.py
odoo/addons/l10n_th_withholding_tax_cert_form/data/mail_template.xml
odoo/addons/l10n_th_withholding_tax_cert_form/data/paper_format.xml
odoo/addons/l10n_th_withholding_tax_cert_form/data/report_data.xml
odoo/addons/l10n_th_withholding_tax_cert_form/data/withholding_tax_cert_data.xml
odoo/addons/l10n_th_withholding_tax_cert_form/i18n/l10n_th_withholding_tax_cert_form.pot
odoo/addons/l10n_th_withholding_tax_cert_form/i18n/th.po
odoo/addons/l10n_th_withholding_tax_cert_form/models/__init__.py
odoo/addons/l10n_th_withholding_tax_cert_form/models/withholding_tax_cert.py
odoo/addons/l10n_th_withholding_tax_cert_form/readme/CONTRIBUTORS.rst
odoo/addons/l10n_th_withholding_tax_cert_form/readme/DESCRIPTION.rst
odoo/addons/l10n_th_withholding_tax_cert_form/readme/USAGE.rst
odoo/addons/l10n_th_withholding_tax_cert_form/reports/__init__.py
odoo/addons/l10n_th_withholding_tax_cert_form/reports/layout.xml
odoo/addons/l10n_th_withholding_tax_cert_form/reports/withholding_report_pdf.py
odoo/addons/l10n_th_withholding_tax_cert_form/static/description/icon.png
odoo/addons/l10n_th_withholding_tax_cert_form/static/description/index.html
odoo/addons/l10n_th_withholding_tax_cert_form/static/fonts/THSarabunNew Bold.ttf
odoo/addons/l10n_th_withholding_tax_cert_form/static/scss/style_report.scss
odoo/addons/l10n_th_withholding_tax_cert_form/static/src/img/WithholdingCert.jpg
odoo/addons/l10n_th_withholding_tax_cert_form/tests/__init__.py
odoo/addons/l10n_th_withholding_tax_cert_form/tests/test_wt_cert_form.py
odoo13_addon_l10n_th_withholding_tax_cert_form-13.0.1.0.3.dist-info/METADATA
odoo13_addon_l10n_th_withholding_tax_cert_form-13.0.1.0.3.dist-info/WHEEL
odoo13_addon_l10n_th_withholding_tax_cert_form-13.0.1.0.3.dist-info/top_level.txt
odoo13_addon_l10n_th_withholding_tax_cert_form-13.0.1.0.3.dist-info/RECORD
