Metadata-Version: 2.1
Name: odoo13-addon-l10n-th-withholding-tax-cert-form
Version: 13.0.1.0.3
Summary: Thai Localization - Withholding Tax Certificate Form
Home-page: https://github.com/OCA/l10n-thailand
Author: Ecosoft, Odoo Community Association (OCA)
Author-email: support@odoo-community.org
License: AGPL-3
Platform: UNKNOWN
Classifier: Programming Language :: Python
Classifier: Framework :: Odoo
Classifier: License :: OSI Approved :: GNU Affero General Public License v3
Requires-Python: >=3.5
Requires-Dist: odoo13-addon-l10n-th-amount-to-text
Requires-Dist: odoo13-addon-l10n-th-withholding-tax-cert
Requires-Dist: odoo (<13.1dev,>=13.0a)
